dms_mediapipe/blaze_face_short_range.tflite
dms_mediapipe/efficientdet.tflite
dms_mediapipe/face_landmarker_v2_with_blendshapes.task
dms_mediapipe/landmarks.py
dms_mediapipe/media_pipe.py
dms_mediapipe-0.0.8.dist-info/METADATA
dms_mediapipe-0.0.8.dist-info/WHEEL
dms_mediapipe-0.0.8.dist-info/entry_points.txt
dms_mediapipe-0.0.8.dist-info/RECORD
