Metadata-Version: 2.1
Name: dms_mediapipe
Version: 0.0.8
Summary: 
Author: Gilad Kutiel
Author-email: giladk@mobileye.com
Requires-Python: ==3.10.*
Classifier: Programming Language :: Python :: 3
Classifier: Programming Language :: Python :: 3.10
Requires-Dist: dms-util (==0.0.*)
Requires-Dist: fire (>=0.5.0,<0.6.0)
Requires-Dist: mediapipe (>=0.10.9,<0.11.0)
Requires-Dist: tqdm (>=4.66.1,<5.0.0)
